jirakosaar/__init__.py
jirakosaar/__main__.py
jirakosaar/__version__.py
jirakosaar/config/__init__.py
jirakosaar/config/configure.py
jirakosaar/issues/__init__.py
jirakosaar/issues/main.py
jirakosaar/issues/auth/__init__.py
jirakosaar/issues/auth/auth.py
jirakosaar-1.0.4.data/scripts/jirakosaar
jirakosaar-1.0.4.dist-info/LICENSE
jirakosaar-1.0.4.dist-info/METADATA
jirakosaar-1.0.4.dist-info/WHEEL
jirakosaar-1.0.4.dist-info/top_level.txt
jirakosaar-1.0.4.dist-info/RECORD
