Metadata-Version: 2.1
Name: jirakosaar
Version: 1.0.4
Summary: Command line tool to get summary of jira issues.
Home-page: https://github.com/diwap/jirakosaar
Author: Diwakar Pandey
Author-email: dexterisdiwap@gmail.com
License: GPL-30.0 License
Project-URL: Source, https://github.com/diwap/jirakosaar
Platform: UNKNOWN
Classifier: Development Status :: 3 - Alpha
Classifier: Intended Audience :: Developers
Classifier: Natural Language :: English
Classifier: License :: OSI Approved :: Apache Software License
Classifier: Programming Language :: Python
Classifier: Programming Language :: Python :: 3.6
Classifier: Programming Language :: Python :: 3.7
Classifier: Programming Language :: Python :: 3.8
Classifier: Programming Language :: Python :: Implementation :: CPython
Classifier: Programming Language :: Python :: Implementation :: PyPy
Requires-Python: >=3.6
Requires-Dist: requests (>=2.0)
